modules/sin.v
module sin(clk, xx);

	parameter N= 4;//5;
	parameter R= 19;
	parameter Rm= R-1;
	
input wire clk;
output wire signed [7:0] xx;

  reg signed [R:0] x,y;
  
assign xx = x[R:R-7];

initial 
begin
	y <= (1<<<Rm)-1;
	x <= 0;
end

always @(posedge clk) begin
	if ( y[R:Rm]== 2'b01 ) begin
		y <= (1<<<Rm)-1;
		x <= 0;
	end	else begin
		x <= ( x + (y>>>N) - (x>>>(2*N+1)) );
		y <= ( y - (x>>>N) - (y>>>(2*N+1)) );
	end
end


endmodule

trunk/benches/sin/testbench.v
module testbench();

reg [6:0] in_val; //7 bit
reg tb_clk;

wire signed [7:0] out_val;
sin sin_gen(tb_clk, out_val);

initial
begin
    $dumpfile("bench.vcd");
    $dumpvars(0,testbench);

    $display("starting testbench!!!!");
	
	tb_clk <= 0;
	repeat (200) begin
		#1;
		tb_clk <= 1;
		#1;
		tb_clk <= 0;
	end
	
    $display("finished OK!");
    $finish;
end
	
endmodule

trunk/benches/sin/bench.vcd
$date
	Thu Nov 27 02:19:06 2014
$end
$version
	Icarus Verilog
$end
$timescale
	1s
$end
$scope module testbench $end
$var wire 8 ! out_val [7:0] $end
$var reg 1 " tb_clk $end
$scope module sin_gen $end
$var wire 1 " clk $end
$var wire 8 # xx [7:0] $end
$var reg 20 $ x [19:0] $end
$var reg 20 % y [19:0] $end
$upscope $end
$upscope $end
$enddefinitions $end
#0
$dumpvars
b111111111111111111 %
b0 $
b0 #
0"
b0 !
$end
#1
b11 !
b11 #
b111111111000000000 %
b11111111111111 $
1"
#2
0"
#3
b111 !
b111 #
b111111100000000010 %
b111111111000000 $
1"
#4
0"
#5
b1011 !
b1011 #
b111110111000001010 %
b1011111100000001 $
1"
#6
0"
#7
b1111 !
b1111 #
b111110000000100011 %
b1111110110000010 $
1"
#8
0"
#9
b10011 !
b10011 #
b111100111001011011 %
b10011101100000110 $
1"
#10
0"
#11
b10111 !
b10111 #
b111011100011000100 %
b10111011101001110 $
1"
#12
0"
#13
b11011 !
b11011 #
b111001111101110100 %
b11011001000011111 $
1"
#14
0"
#15
b11110 !
b11110 #
b111000001010000100 %
b11110101100111101 $
1"
#16
0"
#17
b100010 !
b100010 #
b110110001000010000 %
b100010001001110000 $
1"
#18
0"
#19
b100101 !
b100101 #
b110011111000111000 %
b100101011110000000 $
1"
#20
0"
#21
b101000 !
b101000 #
b110001011100100001 %
b101000101000111000 $
1"
#22
0"
#23
b101011 !
b101011 #
b101110110011110011 %
b101011101001100101 $
1"
#24
0"
#25
b101110 !
b101110 #
b101011111111010111 %
b101110011111010111 $
1"
#26
0"
#27
b110001 !
b110001 #
b101000111111111011 %
b110001001001100001 $
1"
#28
0"
#29
b110011 !
b110011 #
b100101110110001110 %
b110011100111010111 $
1"
#30
0"
#31
b110101 !
b110101 #
b100010100011000011 %
b110101111000010011 $
1"
#32
0"
#33
b110111 !
b110111 #
b11111000111001110 %
b110111111011110000 $
1"
#34
0"
#35
b111001 !
b111001 #
b11011100011100111 %
b111001110001001101 $
1"
#36
0"
#37
b111011 !
b111011 #
b10111111001000111 %
b111011011000001101 $
1"
#38
0"
#39
b111100 !
b111100 #
b10100001000101000 %
b111100110000010110 $
1"
#40
0"
#41
b111101 !
b111101 #
b10000010011000110 %
b111101111001010010 $
1"
#42
0"
#43
b111110 !
b111110 #
b1100011001011111 %
b111110110010101111 $
1"
#44
0"
#45
b111111 !
b111111 #
b1000011100110010 %
b111111011100011110 $
1"
#46
0"
#47
b100011101111110 %
b111111110110010110 $
1"
#48
0"
#49
b1000000 !
b1000000 #
b11110000010 %
b1000000000000001111 $
1"
#50
0"
#51
b111111 !
b111111 #
b11111100011101111111 %
b111111111010000111 $
1"
#52
0"
#53
b11111000011110110100 %
b111111100011111111 $
1"
#54
0"
#55
b111110 !
b111110 #
b11110100100001100010 %
b111110111101111110 $
1"
#56
0"
#57
b11110000100111000111 %
b111110001000001101 $
1"
#58
0"
#59
b111101 !
b111101 #
b11101100110000100011 %
b111101000010111000 $
1"
#60
0"
#61
b111011 !
b111011 #
b11101000111110110010 %
b111011101110010010 $
1"
#62
0"
#63
b111010 !
b111010 #
b11100101010010110010 %
b111010001010110000 $
1"
#64
0"
#65
b111000 !
b111000 #
b11100001101101011101 %
b111000011000101010 $
1"
#66
0"
#67
b110110 !
b110110 #
b11011110001111101110 %
b110110011000011100 $
1"
#68
0"
#69
b110100 !
b110100 #
b11011010111010011100 %
b110100001010100111 $
1"
#70
0"
#71
b110001 !
b110001 #
b11010111101110011011 %
b110001101111101111 $
1"
#72
0"
#73
b101111 !
b101111 #
b11010100101100100000 %
b101111001000011011 $
1"
#74
0"
#75
b101100 !
b101100 #
b11010001110101011010 %
b101100010101010100 $
1"
#76
0"
#77
b101001 !
b101001 #
b11001111001001110111 %
b101001010111000111 $
1"
#78
0"
#79
b100110 !
b100110 #
b11001100101010100010 %
b100110001110100100 $
1"
#80
0"
#81
b100010 !
b100010 #
b11001010011000000011 %
b100010111100011101 $
1"
#82
0"
#83
b11111 !
b11111 #
b11001000010010111111 %
b11111100001100110 $
1"
#84
0"
#85
b11011 !
b11011 #
b11000110011011110111 %
b11011111110110101 $
1"
#86
0"
#87
b11000 !
b11000 #
b11000100110011001001 %
b11000010101000101 $
1"
#88
0"
#89
b10100 !
b10100 #
b11000011011001001111 %
b10100100101001111 $
1"
#90
0"
#91
b10000 !
b10000 #
b11000010001110100000 %
b10000110000001111 $
1"
#92
0"
#93
b1100 !
b1100 #
b11000001010011001111 %
b1100110111000011 $
1"
#94
0"
#95
b1000 !
b1000 #
b11000000100111101001 %
b1000111010101001 $
1"
#96
0"
#97
b100 !
b100 #
b11000000001011111011 %
b100111100000000 $
1"
#98
0"
#99
b0 !
b0 #
b11000000000000001010 %
b111100001000 $
1"
#100
0"
#101
b11111100 !
b11111100 #
b11000000000100011010 %
b11111100111100000001 $
1"
#102
0"
#103
b11111000 !
b11111000 #
b11000000011000101010 %
b11111000111100101011 $
1"
#104
0"
#105
b11110100 !
b11110100 #
b11000000111100110101 %
b11110100111111000110 $
1"
#106
0"
#107
b11110001 !
b11110001 #
b11000001110000110010 %
b11110001000100010010 $
1"
#108
0"
#109
b11101101 !
b11101101 #
b11000010110100010011 %
b11101101001101001101 $
1"
#110
0"
#111
b11101001 !
b11101001 #
b11000100000111001001 %
b11101001011010110101 $
1"
#112
0"
#113
b11100101 !
b11100101 #
b11000101101000111110 %
b11100101101110000110 $
1"
#114
0"
#115
b11100010 !
b11100010 #
b11000111011001011001 %
b11100010000111111100 $
1"
#116
0"
#117
b11011110 !
b11011110 #
b11001001010111111111 %
b11011110101001010001 $
1"
#118
0"
#119
b11011011 !
b11011011 #
b11001011100100010000 %
b11011011010010111011 $
1"
#120
0"
#121
b11011000 !
b11011000 #
b11001101111101101001 %
b11011000000101110010 $
1"
#122
0"
#123
b11010101 !
b11010101 #
b11010000100011100011 %
b11010101000010101000 $
1"
#124
0"
#125
b11010010 !
b11010010 #
b11010011010101010101 %
b11010010001010001110 $
1"
#126
0"
#127
b11001111 !
b11001111 #
b11010110010010010011 %
b11001111011101010010 $
1"
#128
0"
#129
b11001100 !
b11001100 #
b11011001011001101100 %
b11001100111100100000 $
1"
#130
0"
#131
b11001010 !
b11001010 #
b11011100101010101111 %
b11001010101000011111 $
1"
#132
0"
#133
b11001000 !
b11001000 #
b11100000000100101001 %
b11001000100001110100 $
1"
#134
0"
#135
b11000110 !
b11000110 #
b11100011100110100010 %
b11000110101001000010 $
1"
#136
0"
#137
b11000100 !
b11000100 #
b11100111001111100010 %
b11000100111110100111 $
1"
#138
0"
#139
b11000011 !
b11000011 #
b11101010111110101111 %
b11000011100010111110 $
1"
#140
0"
#141
b11000010 !
b11000010 #
b11101110110011001101 %
b11000010010110011100 $
1"
#142
0"
#143
b11000001 !
b11000001 #
b11110010101011111110 %
b11000001011001010110 $
1"
#144
0"
#145
b11000000 !
b11000000 #
b11110110101000000100 %
b11000000101011111010 $
1"
#146
0"
#147
b11111010100110100000 %
b11000000001110010101 $
1"
#148
0"
#149
b11111110100110010011 %
b11000000000000101110 $
1"
#150
0"
#151
b10100110011101 %
b11000000000011000111 $
1"
#152
0"
#153
b110100101111101 %
b11000000010101100000 $
1"
#154
0"
#155
b1010100011110011 %
b11000000110111110101 $
1"
#156
0"
#157
b11000001 !
b11000001 #
b1110011111000000 %
b11000001101001111110 $
1"
#158
0"
#159
b11000010 !
b11000010 #
b10010010110100110 %
b11000010101011101101 $
1"
#160
0"
#161
b11000011 !
b11000011 #
b10110001001100110 %
b11000011111100110010 $
1"
#162
0"
#163
b11000101 !
b11000101 #
b11001110111000010 %
b11000101011100111001 $
1"
#164
0"
#165
b11000111 !
b11000111 #
b11101011110000001 %
b11000111001011101010 $
1"
#166
0"
#167
b11001001 !
b11001001 #
b100000111101101000 %
b11001001001000101001 $
1"
#168
0"
#169
b11001011 !
b11001011 #
b100100010100111111 %
b11001011010011010110 $
1"
#170
0"
#171
b11001101 !
b11001101 #
b100111100011010000 %
b11001101101011001111 $
1"
#172
0"
#173
b11010000 !
b11010000 #
b101010100111101000 %
b11010000001111101111 $
1"
#174
0"
#175
b11010011 !
b11010011 #
b101101100001010110 %
b11010011000000001100 $
1"
#176
0"
#177
b11010101 !
b11010101 #
b110000001111101010 %
b11010101111011111001 $
1"
#178
0"
#179
b11011001 !
b11011001 #
b110010110001111010 %
b11011001000010001000 $
1"
#180
0"
#181
b11011100 !
b11011100 #
b110101000111011100 %
b11011100010010000111 $
1"
#182
0"
#183
b11011111 !
b11011111 #
b110111001111101100 %
b11011111101011000010 $
1"
#184
0"
#185
b11100011 !
b11100011 #
b111001001010000111 %
b11100011001100000011 $
1"
#186
0"
#187
b11100110 !
b11100110 #
b111010110110001110 %
b11100110110100010010 $
1"
#188
0"
#189
b11101010 !
b11101010 #
b111100010011100111 %
b11101010100010110100 $
1"
#190
0"
#191
b11101110 !
b11101110 #
b111101100001111010 %
b11101110010110101110 $
1"
#192
0"
#193
b11110010 !
b11110010 #
b111110100000110100 %
b11110010001111000011 $
1"
#194
0"
#195
b11110110 !
b11110110 #
b111111010000000100 %
b11110110001010110101 $
1"
#196
0"
#197
b11111010 !
b11111010 #
b111111101111011111 %
b11111010001001000100 $
1"
#198
0"
#199
b11111110 !
b11111110 #
b111111111110111110 %
b11111110001000110000 $
1"
#200
0"
#201
b10 !
b10 #
b111111111110011100 %
b10001000111010 $
1"
#202
0"
#203
b110 !
b110 #
b111111101101111010 %
b110001000100010 $
1"
#204
0"
#205
b1010 !
b1010 #
b111111001101011011 %
b1010000110101000 $
1"
#206
0"
#207
b1110 !
b1110 #
b111110011101001000 %
b1110000010001101 $
1"
#208
0"
#209
b10001 !
b10001 #
b111101011101001101 %
b10001111010010001 $
1"
#210
0"
#211
b10101 !
b10101 #
b111100001101111001 %
b10101101101110110 $
1"
#212
0"
#213
b11001 !
b11001 #
b111010101111100001 %
b11001011100000000 $
1"
#214
0"
#215
b11101 !
b11101 #
b111001000010011100 %
b11101000011110011 $
1"
#216
0"
#217
b100000 !
b100000 #
b110111000111000101 %
b100000100100010100 $
1"
#218
0"
#219
b100011 !
b100011 #
b110100111101111100 %
b100011111100101100 $
1"
#220
0"
#221
b100111 !
b100111 #
b110010100111100011 %
b100111001100000100 $
1"
#222
0"
#223
b101010 !
b101010 #
b110000000100011111 %
b101010010001101001 $
1"
#224
0"
#225
b101101 !
b101101 #
b101101010101011001 %
b101101001100101000 $
1"
#226
0"
#227
b101111 !
b101111 #
b101010011010111101 %
b101111111100010100 $
1"
#228
0"
#229
b110010 !
b110010 #
b100111010101111001 %
b110010100000000000 $
1"
#230
0"
#231
b110100 !
b110100 #
b100100000110111111 %
b110100110111000011 $
1"
#232
0"
#233
b110111 !
b110111 #
b100000101111000011 %
b110111000000111000 $
1"
#234
0"
#235
b111000 !
b111000 #
b11101001110111011 %
b111000111100111100 $
1"
#236
0"
#237
b111010 !
b111010 #
b11001100111011111 %
b111010101010110000 $
1"
#238
0"
#239
b111100 !
b111100 #
b10101111001101000 %
b111100001001111000 $
1"
#240
0"
#241
b111101 !
b111101 #
b10010000110010010 %
b111101011001111101 $
1"
#242
0"
#243
b111110 !
b111110 #
b1110001110011011 %
b111110011010101011 $
1"
#244
0"
#245
b111111 !
b111111 #
b1010010011000000 %
b111111001011110001 $
1"
#246
0"
#247
b110010100111111 %
b111111101101000100 $
1"
#248
0"
#249
b10010101011001 %
b111111111110011010 $
1"
#250
0"
#251
b11111110010101001110 %
b111111111111110000 $
1"
#252
0"
#253
b11111010010101011101 %
b111111110001000101 $
1"
#254
0"
#255
b11110110010111000111 %
b111111010010011100 $
1"
#256
0"
#257
b111110 !
b111110 #
b11110010011011001100 %
b111110100011111110 $
1"
#258
0"
#259
b111101 !
b111101 #
b11101110100010101010 %
b111101100101110110 $
1"
#260
0"
#261
b111100 !
b111100 #
b11101010101110011111 %
b111100011000010100 $
1"
#262
0"
#263
b111010 !
b111010 #
b11100110111111101001 %
b111010111011101010 $
1"
#264
0"
#265
b111001 !
b111001 #
b11100011010111000100 %
b111001010000010001 $
1"
#266
0"
#267
b110111 !
b110111 #
b11011111110101101001 %
b110111010110100011 $
1"
#268
0"
#269
b110101 !
b110101 #
b11011100011100010001 %
b110101001110111111 $
1"
#270
0"
#271
b110010 !
b110010 #
b11011001001011110011 %
b110010111010000111 $
1"
#272
0"
#273
b110000 !
b110000 #
b11010110000101000010 %
b110000011000011111 $
1"
#274
0"
#275
b101101 !
b101101 #
b11010011001000110001 %
b101101101010110000 $
1"
#276
0"
#277
b101010 !
b101010 #
b11010000010111101101 %
b101010110001100110 $
1"
#278
0"
#279
b100111 !
b100111 #
b11001101110010100101 %
b100111101101101110 $
1"
#280
0"
#281
b100100 !
b100100 #
b11001011011010000001 %
b100100011111111011 $
1"
#282
0"
#283
b100001 !
b100001 #
b11001001001110100111 %
b100001001001000000 $
1"
#284
0"
#285
b11101 !
b11101 #
b11000111010000111010 %
b11101101001110001 $
1"
#286
0"
#287
b11010 !
b11010 #
b11000101100001011001 %
b11010000011000111 $
1"
#288
0"
#289
b10110 !
b10110 #
b11000100000000100001 %
b10110010101111100 $
1"
#290
0"
#291
b10010 !
b10010 #
b11000010101110101010 %
b10010100011001100 $
1"
#292
0"
#293
b1110 !
b1110 #
b11000001101100001001 %
b1110101011110010 $
1"
#294
0"
#295
b1010 !
b1010 #
b11000000111001001101 %
b1010110000101101 $
1"
#296
0"
#297
b110 !
b110 #
b11000000010110000100 %
b110110010111011 $
1"
#298
0"
#299
b10 !
b10 #
b11000000000010110111 %
b10110011011101 $
1"
#300
0"
#301
b11111110 !
b11111110 #
b10111111111111101010 %
b11111110110011010010 $
1"
#302
0"
#303
b11111010 !
b11111010 #
b11000000001100011110 %
b11111010110011011010 $
1"
#304
0"
#305
b11110110 !
b11110110 #
b11000000101001010000 %
b11110110110100110101 $
1"
#306
0"
#307
b11110010 !
b11110010 #
b11000001010101111000 %
b11110010111000100100 $
1"
#308
0"
#309
b11101110 !
b11101110 #
b11000010010010001100 %
b11101110111111100100 $
1"
#310
0"
#311
b11101011 !
b11101011 #
b11000011011101111100 %
b11101011001010110101 $
1"
#312
0"
#313
b11100111 !
b11100111 #
b11000100111000110110 %
b11100111011011010011 $
1"
#314
0"
#315
b11100011 !
b11100011 #
b11000110100010100010 %
b11100011110001111011 $
1"
#316
0"
#317
b11100000 !
b11100000 #
b11001000011010100111 %
b11100000001111100111 $
1"
#318
0"
#319
b11011100 !
b11011100 #
b11001010100000100110 %
b11011100110101010000 $
1"
#320
0"
#321
b11011001 !
b11011001 #
b11001100110011111101 %
b11011001100011101100 $
1"
#322
0"
#323
b11010110 !
b11010110 #
b11001111010100001001 %
b11010110011011101111 $
1"
#324
0"
#325
b11010011 !
b11010011 #
b11010010000000100001 %
b11010011011110001100 $
1"
#326
0"
#327
b11010000 !
b11010000 #
b11010100111000011001 %
b11010000101011110011 $
1"
#328
0"
#329
b11001110 !
b11001110 #
b11010111111011000011 %
b11001110000101001111 $
1"
#330
0"
#331
b11001011 !
b11001011 #
b11011011000111110000 %
b11001011101011001011 $
1"
#332
0"
#333
b11001001 !
b11001001 #
b11011110011101101100 %
b11001001011110001101 $
1"
#334
0"
#335
b11000111 !
b11000111 #
b11100001111100000001 %
b11000111011110111000 $
1"
#336
0"
#337
b11000101 !
b11000101 #
b11100101100001110111 %
b11000101101101101101 $
1"
#338
0"
#339
b11000100 !
b11000100 #
b11101001001110010101 %
b11000100001011000111 $
1"
#340
0"
#341
b11000010 !
b11000010 #
b11101101000000100000 %
b11000010110111011111 $
1"
#342
0"
#343
b11000001 !
b11000001 #
b11110000110111011011 %
b11000001110011001011 $
1"
#344
0"
#345
b11000000 !
b11000000 #
b11110100110010001001 %
b11000000111110011010 $
1"
#346
0"
#347
b11111000101111101010 %
b11000000011001011011 $
1"
#348
0"
#349
b11111100101111000000 %
b11000000000100010110 $
1"
#350
0"
#351
b10111111 !
b10111111 #
b101111001010 %
b10111111111111010010 $
1"
#352
0"
#353
b11000000 !
b11000000 #
b100101111001000 %
b11000000001010001111 $
1"
#354
0"
#355
b1000101101111011 %
b11000000100101001010 $
1"
#356
0"
#357
b11000001 !
b11000001 #
b1100101010100010 %
b11000001001111111101 $
1"
#358
0"
#359
b11000010 !
b11000010 #
b10000100011111110 %
b11000010001010011110 $
1"
#360
0"
#361
b11000011 !
b11000011 #
b10100011001010001 %
b11000011010100011100 $
1"
#362
0"
#363
b11000100 !
b11000100 #
b11000001001011101 %
b11000100101101100111 $
1"
#364
0"
#365
b11000110 !
b11000110 #
b11011110011100110 %
b11000110010101100111 $
1"
#366
0"
#367
b11001000 !
b11001000 #
b11111010110110010 %
b11001000001100000011 $
1"
#368
0"
#369
b11001010 !
b11001010 #
b100010110010001000 %
b11001010010000011101 $
1"
#370
0"
#371
b11001100 !
b11001100 #
b100110000100110001 %
b11001100100010010011 $
1"
#372
0"
#373
b11001111 !
b11001111 #
b101001001101111000 %
b11001111000001000010 $
1"
#374
0"
#375
b11010001 !
b11010001 #
b101100001100101011 %
b11010001101100000001 $
1"
#376
0"
#377
b11010100 !
b11010100 #
b101111000000011010 %
b11010100100010100110 $
1"
#378
0"
#379
b11010111 !
b11010111 #
b110001101000011000 %
b11010111100100000011 $
1"
#380
0"
#381
b11011010 !
b11011010 #
b110100000011111011 %
b11011010101111101000 $
1"
#382
0"
#383
b11011110 !
b11011110 #
b110110010010011101 %
b11011110000100100010 $
1"
#384
0"
#385
b11100001 !
b11100001 #
b111000010011011001 %
b11100001100001111011 $
1"
#386
0"
#387
b11100101 !
b11100101 #
b111010000110010000 %
b11100101000110111100 $
1"
#388
0"
#389
b11101000 !
b11101000 #
b111011101010100101 %
b11101000110010101101 $
1"
#390
0"
#391
b11101100 !
b11101100 #
b111100111111111110 %
b11101100100100010001 $
1"
#392
0"
#393
b11110000 !
b11110000 #
b111110000110000110 %
b11110000011010101100 $
1"
#394
0"
#395
b11110100 !
b11110100 #
b111110111100101100 %
b11110100010101000001 $
1"
#396
0"
#397
b11111000 !
b11111000 #
b111111100011100001 %
b11111000010010010001 $
1"
#398
0"
#399
b11111100 !
b11111100 #
b111111111010011100 %
b11111100010001011101 $
1"
