modules/rnd8.v
module rnd8(clk, sout);

input wire clk;
output reg [7:0] sout;

reg [31:0] d0;
reg [31:0] d1;
reg [31:0] d2;
reg [31:0] d3;
reg [31:0] d4;
reg [31:0] d5;
reg [31:0] d6;
reg [31:0] d7;

initial
begin
  sout <= 8'd0;
  d0 <= 31'b0011010100100100110010101110010;
  d1 <= 31'b0101010101010010101010010110010;
  d2 <= 31'b0101010010101010101010100101010;
  d3 <= 31'b0101010011001100101010110010101;
  d4 <= 31'b0101010010101010101011001010110;
  d5 <= 31'b1001001011001010100101101010100;
  d6 <= 31'b0101010100100110100101010101010;
  d7 <= 31'b0101010010101010110100101010101;
end

always @(posedge clk) begin 
	d0 <= { d0[30:0], d0[30] ^ d0[27] };
	d1 <= { d1[30:0], d1[30] ^ d1[27] };
	d2 <= { d2[30:0], d2[30] ^ d2[27] };
	d3 <= { d3[30:0], d3[30] ^ d3[27] };
	d4 <= { d4[30:0], d4[30] ^ d4[27] };
	d5 <= { d5[30:0], d5[30] ^ d5[27] };
	d6 <= { d6[30:0], d6[30] ^ d6[27] };
	d7 <= { d7[30:0], d7[30] ^ d7[27] };
	
	sout <= {d0[5:5],d1[5:5],d2[5:5],d3[5:5],d4[5:5],d5[5:5],d6[5:5],d7[5:5]};

end

endmodule

benches/rnd8/testbench.v
module testbench();

reg [6:0] in_val; //7 bit
reg tb_clk;

wire [7:0] out_val;
rnd8 rnd8_gen(tb_clk, out_val);

initial
begin
    $dumpfile("bench.vcd");
    $dumpvars(0,testbench);

    $display("starting testbench!!!!");
	
	tb_clk <= 0;
	repeat (2000) begin
		#1;
		tb_clk <= 1;
		#1;
		tb_clk <= 0;
	end
	
    $display("finished OK!");
    $finish;
end
	
endmodule

trunk/benches/rnd8/bench.vcd
$date
	Wed Nov 12 23:05:18 2014
$end
$version
	Icarus Verilog
$end
$timescale
	1s
$end
$scope module testbench $end
$var wire 8 ! out_val [7:0] $end
$var reg 1 " tb_clk $end
$scope module rnd8_gen $end
$var wire 1 " clk $end
$var reg 32 # d0 [31:0] $end
$var reg 32 $ d1 [31:0] $end
$var reg 32 % d2 [31:0] $end
$var reg 32 & d3 [31:0] $end
$var reg 32 ' d4 [31:0] $end
$var reg 32 ( d5 [31:0] $end
$var reg 32 ) d6 [31:0] $end
$var reg 32 * d7 [31:0] $end
$var reg 8 + sout [7:0] $end
$upscope $end
$upscope $end
$enddefinitions $end
#0
$dumpvars
b0 +
b101010010101010110100101010101 *
b101010100100110100101010101010 )
b1001001011001010100101101010100 (
b101010010101010101011001010110 '
b101010011001100101010110010101 &
b101010010101010101010100101010 %
b101010101010010101010010110010 $
b11010100100100110010101110010 #
0"
b0 !
$end
#1
b11100010 !
b11100010 +
b1010100101010101101001010101011 *
b1010101001001101001010101010101 )
b10010010110010101001011010101000 (
b1010100101010101010110010101101 '
b1010100110011001010101100101011 &
b1010100101010101010101001010101 %
b1010101010100101010100101100101 $
b110101001001001100101011100101 #
1"
#2
0"
#3
b11011101 !
b11011101 +
b10101001010101011010010101010111 *
b10101010010011010010101010101011 )
b100101100101010010110101010000 (
b10101001010101010101100101011011 '
b10101001100110010101011001010111 &
b10101001010101010101010010101011 %
b10101010101001010101001011001011 $
b1101010010010011001010111001010 #
1"
#4
0"
#5
b100010 !
b100010 +
b1010010101010110100101010101111 *
b1010100100110100101010101010111 )
b1001011001010100101101010100000 (
b1010010101010101011001010110111 '
b1010011001100101010110010101111 &
b1010010101010101010100101010111 %
b1010101010010101010010110010111 $
b11010100100100110010101110010100 #
1"
#6
0"
#7
b11101 !
b11101 +
b10100101010101101001010101011111 *
b10101001001101001010101010101111 )
b10010110010101001011010101000000 (
b10100101010101010110010101101111 '
b10100110011001010101100101011111 &
b10100101010101010101001010101111 %
b10101010100101010100101100101111 $
b10101001001001100101011100101001 #
1"
#8
0"
#9
b11101010 !
b11101010 +
b1001010101011010010101010111110 *
b1010010011010010101010101011111 )
b101100101010010110101010000000 (
b1001010101010101100101011011110 '
b1001100110010101011001010111110 &
b1001010101010101010010101011110 %
b1010101001010101001011001011111 $
b1010010010011001010111001010011 #
1"
#10
0"
#11
b10001 !
b10001 +
b10010101010110100101010101111100 *
b10100100110100101010101010111111 )
b1011001010100101101010100000001 (
b10010101010101011001010110111100 '
b10011001100101010110010101111100 &
b10010101010101010100101010111100 %
b10101010010101010010110010111111 $
b10100100100110010101110010100111 #
1"
#12
0"
#13
b11111011 !
b11111011 +
b101010101101001010101011111000 *
b1001001101001010101010101111110 )
b10110010101001011010101000000010 (
b101010101010110010101101111000 '
b110011001010101100101011111001 &
b101010101010101001010101111000 %
b1010100101010100101100101111111 $
b1001001001100101011100101001110 #
1"
#14
0"
#15
b1111011 !
b1111011 +
b1010101011010010101010111110001 *
b10010011010010101010101011111100 )
b1100101010010110101010000000100 (
b1010101010101100101011011110001 '
b1100110010101011001010111110010 &
b1010101010101010010101011110001 %
b10101001010101001011001011111111 $
b10010010011001010111001010011100 #
1"
#16
0"
#17
b10101010110100101010101111100011 *
b100110100101010101010111111000 )
b11001010100101101010100000001001 (
b10101010101011001010110111100011 '
b11001100101010110010101111100101 &
b10101010101010100101010111100011 %
b1010010101010010110010111111111 $
b100100110010101110010100111000 #
1"
#18
0"
#19
b11111011 !
b11111011 +
b1010101101001010101011111000111 *
b1001101001010101010101111110000 )
b10010101001011010101000000010010 (
b1010101010110010101101111000111 '
b10011001010101100101011111001010 &
b1010101010101001010101111000111 %
b10100101010100101100101111111111 $
b1001001100101011100101001110000 #
1"
#20
0"
#21
b11000010 !
b11000010 +
b10101011010010101010111110001111 *
b10011010010101010101011111100000 )
b101010010110101010000000100100 (
b10101010101100101011011110001111 '
b110010101011001010111110010101 &
b10101010101010010101011110001111 %
b1001010101001011001011111111110 $
b10010011001010111001010011100000 #
1"
#22
0"
#23
b11000110 !
b11000110 +
b1010110100101010101111100011111 *
b110100101010101010111111000001 )
b1010100101101010100000001001001 (
b1010101011001010110111100011111 '
b1100101010110010101111100101010 &
b1010101010100101010111100011111 %
b10010101010010110010111111111100 $
b100110010101110010100111000000 #
1"
#24
0"
#25
b1010000 !
b1010000 +
b10101101001010101011111000111111 *
b1101001010101010101111110000010 )
b10101001011010101000000010010011 (
b10101010110010101101111000111111 '
b11001010101100101011111001010101 &
b10101010101001010101111000111111 %
b101010100101100101111111111000 $
b1001100101011100101001110000000 #
1"
#26
0"
#27
b1101001 !
b1101001 +
b1011010010101010111110001111111 *
b11010010101010101011111100000100 )
b1010010110101010000000100100111 (
b1010101100101011011110001111111 '
b10010101011001010111110010101010 &
b1010101010010101011110001111111 %
b1010101001011001011111111110001 $
b10011001010111001010011100000000 #
1"
#28
0"
#29
b1111101 !
b1111101 +
b10110100101010101111100011111110 *
b10100101010101010111111000001001 )
b10100101101010100000001001001111 (
b10101011001010110111100011111111 '
b101010110010101111100101010100 &
b10101010100101010111100011111111 %
b10101010010110010111111111100011 $
b110010101110010100111000000001 #
1"
#30
0"
#31
b1101001 !
b1101001 +
b1101001010101011111000111111100 *
b1001010101010101111110000010010 )
b1001011010101000000010010011110 (
b1010110010101101111000111111111 '
b1010101100101011111001010101001 &
b1010101001010101111000111111111 %
b1010100101100101111111111000111 $
b1100101011100101001110000000010 #
1"
#32
0"
#33
b111001 !
b111001 +
b11010010101010111110001111111000 *
b10010101010101011111100000100100 )
b10010110101010000000100100111100 (
b10101100101011011110001111111111 '
b10101011001010111110010101010011 &
b10101010010101011110001111111111 %
b10101001011001011111111110001111 $
b11001010111001010011100000000101 #
1"
#34
0"
#35
b101111 !
b101111 +
b10100101010101111100011111110001 *
b101010101010111111000001001000 )
b101101010100000001001001111000 (
b1011001010110111100011111111111 '
b1010110010101111100101010100111 &
b1010100101010111100011111111111 %
b1010010110010111111111100011111 $
b10010101110010100111000000001010 #
1"
#36
0"
#37
b111101 !
b111101 +
b1001010101011111000111111100010 *
b1010101010101111110000010010001 )
b1011010101000000010010011110001 (
b10110010101101111000111111111110 '
b10101100101011111001010101001111 &
b10101001010101111000111111111111 %
b10100101100101111111111000111111 $
b101011100101001110000000010100 #
1"
#38
0"
#39
b1101101 !
b1101101 +
b10010101010111110001111111000100 *
b10101010101011111100000100100011 )
b10110101010000000100100111100010 (
b1100101011011110001111111111100 '
b1011001010111110010101010011111 &
b1010010101011110001111111111111 %
b1001011001011111111110001111110 $
b1010111001010011100000000101001 #
1"
#40
0"
#41
b11101110 !
b11101110 +
b101010101111100011111110001000 *
b1010101010111111000001001000111 )
b1101010100000001001001111000100 (
b11001010110111100011111111111001 '
b10110010101111100101010100111110 &
b10100101010111100011111111111111 %
b10010110010111111111100011111100 $
b10101110010100111000000001010011 #
1"
#42
0"
#43
b1111000 !
b1111000 +
b1010101011111000111111100010001 *
b10101010101111110000010010001111 )
b11010101000000010010011110001000 (
b10010101101111000111111111110010 '
b1100101011111001010101001111100 &
b1001010101111000111111111111110 %
b101100101111111111000111111000 $
b1011100101001110000000010100111 #
1"
#44
0"
#45
b11111000 !
b11111000 +
b10101010111110001111111000100011 *
b1010101011111100000100100011111 )
b10101010000000100100111100010001 (
b101011011110001111111111100100 '
b11001010111110010101010011111001 &
b10010101011110001111111111111100 %
b1011001011111111110001111110001 $
b10111001010011100000000101001110 #
1"
#46
0"
#47
b1111001 !
b1111001 +
b1010101111100011111110001000111 *
b10101010111111000001001000111111 )
b1010100000001001001111000100011 (
b1010110111100011111111111001001 '
b10010101111100101010100111110010 &
b101010111100011111111111111000 %
b10110010111111111100011111100010 $
b1110010100111000000001010011101 #
1"
#48
0"
#49
b1110110 !
b1110110 +
b10101011111000111111100010001111 *
b1010101111110000010010001111111 )
b10101000000010010011110001000111 (
b10101101111000111111111110010011 '
b101011111001010101001111100100 &
b1010101111000111111111111110001 %
b1100101111111111000111111000100 $
b11100101001110000000010100111011 #
1"
#50
0"
#51
b10110010 !
b10110010 +
b1010111110001111111000100011111 *
b10101011111100000100100011111111 )
b1010000000100100111100010001111 (
b1011011110001111111111100100111 '
b1010111110010101010011111001001 &
b10101011110001111111111111100011 %
b11001011111111110001111110001001 $
b11001010011100000000101001110111 #
1"
#52
0"
#53
b10101010 !
b10101010 +
b10101111100011111110001000111111 *
b1010111111000001001000111111111 )
b10100000001001001111000100011111 (
b10110111100011111111111001001110 '
b10101111100101010100111110010011 &
b1010111100011111111111111000111 %
b10010111111111100011111100010010 $
b10010100111000000001010011101110 #
1"
#54
0"
#55
b10000011 !
b10000011 +
b1011111000111111100010001111111 *
b10101111110000010010001111111111 )
b1000000010010011110001000111110 (
b1101111000111111111110010011100 '
b1011111001010101001111100100111 &
b10101111000111111111111110001111 %
b101111111111000111111000100100 $
b101001110000000010100111011100 #
1"
#56
0"
#57
b1010111 !
b1010111 +
b10111110001111111000100011111110 *
b1011111100000100100011111111111 )
b10000000100100111100010001111101 (
b11011110001111111111100100111000 '
b10111110010101010011111001001110 &
b1011110001111111111111100011111 %
b1011111111110001111110001001001 $
b1010011100000000101001110111001 #
1"
#58
0"
#59
b10001111 !
b10001111 +
b1111100011111110001000111111101 *
b10111111000001001000111111111110 )
b1001001111000100011111010 (
b10111100011111111111001001110000 '
b1111100101010100111110010011101 &
b10111100011111111111111000111110 %
b10111111111100011111100010010010 $
b10100111000000001010011101110011 #
1"
#60
0"
#61
b10101111 !
b10101111 +
b11111000111111100010001111111010 *
b1111110000010010001111111111101 )
b10010011110001000111110100 (
b1111000111111111110010011100001 '
b11111001010101001111100100111010 &
b1111000111111111111110001111101 %
b1111111111000111111000100100101 $
b1001110000000010100111011100110 #
1"
#62
0"
#63
b11111111 !
b11111111 +
b11110001111111000100011111110100 *
b11111100000100100011111111111010 )
b100100111100010001111101000 (
b11110001111111111100100111000010 '
b11110010101010011111001001110100 &
b11110001111111111111100011111010 %
b11111111110001111110001001001010 $
b10011100000000101001110111001100 #
1"
#64
0"
#65
b110111 !
b110111 +
b11100011111110001000111111101001 *
b11111000001001000111111111110100 )
b1001001111000100011111010000 (
b11100011111111111001001110000101 '
b11100101010100111110010011101001 &
b11100011111111111111000111110101 %
b11111111100011111100010010010100 $
b111000000001010011101110011001 #
1"
#66
0"
#67
b110011 !
b110011 +
b11000111111100010001111111010011 *
b11110000010010001111111111101000 )
b10010011110001000111110100001 (
b11000111111111110010011100001011 '
b11001010101001111100100111010011 &
b11000111111111111110001111101011 %
b11111111000111111000100100101000 $
b1110000000010100111011100110011 #
1"
#68
0"
#69
b11100110 !
b11100110 +
b10001111111000100011111110100111 *
b11100000100100011111111111010001 )
b100100111100010001111101000010 (
b10001111111111100100111000010111 '
b10010101010011111001001110100110 &
b10001111111111111100011111010111 %
b11111110001111110001001001010000 $
b11100000000101001110111001100111 #
1"
#70
0"
#71
b10010001 !
b10010001 +
b11111110001000111111101001111 *
b11000001001000111111111110100011 )
b1001001111000100011111010000100 (
b11111111111001001110000101111 '
b101010100111110010011101001100 &
b11111111111111000111110101111 %
b11111100011111100010010010100000 $
b11000000001010011101110011001111 #
1"
#72
0"
#73
b1101010 !
b1101010 +
b111111100010001111111010011111 *
b10000010010001111111111101000111 )
b10010011110001000111110100001000 (
b111111111110010011100001011111 '
b1010101001111100100111010011001 &
b111111111111110001111101011111 %
b11111000111111000100100101000000 $
b10000000010100111011100110011111 #
1"
#74
0"
#75
b0 !
b0 +
b1111111000100011111110100111111 *
b100100011111111111010001110 )
b100111100010001111101000010000 (
b1111111111100100111000010111111 '
b10101010011111001001110100110011 &
b1111111111111100011111010111111 %
b11110001111110001001001010000000 $
b101001110111001100111110 #
1"
#76
0"
#77
b10111001 !
b10111001 +
b11111110001000111111101001111110 *
b1001000111111111110100011100 )
b1001111000100011111010000100000 (
b11111111111001001110000101111110 '
b1010100111110010011101001100111 &
b11111111111111000111110101111110 %
b11100011111100010010010100000001 $
b1010011101110011001111100 #
1"
#78
0"
#79
b10111101 !
b10111101 +
b11111100010001111111010011111100 *
b10010001111111111101000111001 )
b10011110001000111110100001000000 (
b11111111110010011100001011111100 '
b10101001111100100111010011001111 &
b11111111111110001111101011111100 %
b11000111111000100100101000000011 $
b10100111011100110011111000 #
1"
#80
0"
#81
b10101011 !
b10101011 +
b11111000100011111110100111111000 *
b100100011111111111010001110010 )
b111100010001111101000010000001 (
b11111111100100111000010111111000 '
b1010011111001001110100110011111 &
b11111111111100011111010111111000 %
b10001111110001001001010000000111 $
b101001110111001100111110000 #
1"
#82
0"
#83
b11110001000111111101001111110000 *
b1001000111111111110100011100100 )
b1111000100011111010000100000011 (
b11111111001001110000101111110000 '
b10100111110010011101001100111111 &
b11111111111000111110101111110000 %
b11111100010010010100000001111 $
b1010011101110011001111100000 #
1"
#84
0"
#85
b10111011 !
b10111011 +
b11100010001111111010011111100001 *
b10010001111111111101000111001000 )
b11110001000111110100001000000110 (
b11111110010011100001011111100000 '
b1001111100100111010011001111110 &
b11111111110001111101011111100000 %
b111111000100100101000000011111 $
b10100111011100110011111000001 #
1"
#86
0"
#87
b111001 !
b111001 +
b11000100011111110100111111000011 *
b100011111111111010001110010000 )
b11100010001111101000010000001101 (
b11111100100111000010111111000000 '
b10011111001001110100110011111100 &
b11111111100011111010111111000000 %
b1111110001001001010000000111111 $
b101001110111001100111110000010 #
1"
#88
0"
#89
b1010000 !
b1010000 +
b10001000111111101001111110000111 *
b1000111111111110100011100100000 )
b11000100011111010000100000011011 (
b11111001001110000101111110000000 '
b111110010011101001100111111001 &
b11111111000111110101111110000000 %
b11111100010010010100000001111110 $
b1010011101110011001111100000101 #
1"
#90
0"
#91
b1010010 !
b1010010 +
b10001111111010011111100001111 *
b10001111111111101000111001000001 )
b10001000111110100001000000110111 (
b11110010011100001011111100000000 '
b1111100100111010011001111110011 &
b11111110001111101011111100000000 %
b11111000100100101000000011111100 $
b10100111011100110011111000001011 #
1"
#92
0"
#93
b1010100 !
b1010100 +
b100011111110100111111000011110 *
b11111111111010001110010000011 )
b10001111101000010000001101111 (
b11100100111000010111111000000001 '
b11111001001110100110011111100110 &
b11111100011111010111111000000000 %
b11110001001001010000000111111000 $
b1001110111001100111110000010110 #
1"
#94
0"
#95
b1000111111101001111110000111100 *
b111111111110100011100100000111 )
b100011111010000100000011011110 (
b11001001110000101111110000000011 '
b11110010011101001100111111001100 &
b11111000111110101111110000000000 %
b11100010010010100000001111110001 $
b10011101110011001111100000101100 #
1"
#96
0"
#97
b11000001 !
b11000001 +
b10001111111010011111100001111001 *
b1111111111101000111001000001111 )
b1000111110100001000000110111100 (
b10010011100001011111100000000110 '
b11100100111010011001111110011001 &
b11110001111101011111100000000000 %
b11000100100101000000011111100011 $
b111011100110011111000001011001 #
1"
#98
0"
#99
b1000101 !
b1000101 +
b11111110100111111000011110011 *
b11111111111010001110010000011110 )
b10001111101000010000001101111001 (
b100111000010111111000000001100 '
b11001001110100110011111100110011 &
b11100011111010111111000000000001 %
b10001001001010000000111111000111 $
b1110111001100111110000010110011 #
1"
#100
0"
#101
b10010101 !
b10010101 +
b111111101001111110000111100111 *
b11111111110100011100100000111100 )
b11111010000100000011011110011 (
b1001110000101111110000000011000 '
b10010011101001100111111001100110 &
b11000111110101111110000000000011 %
b10010010100000001111110001111 $
b11101110011001111100000101100111 #
1"
#102
0"
#103
b10010111 !
b10010111 +
b1111111010011111100001111001111 *
b11111111101000111001000001111000 )
b111110100001000000110111100111 (
b10011100001011111100000000110000 '
b100111010011001111110011001100 &
b10001111101011111100000000000111 %
b100100101000000011111100011110 $
b11011100110011111000001011001110 #
1"
#104
0"
#105
b1110 !
b1110 +
b11111110100111111000011110011110 *
b11111111010001110010000011110000 )
b1111101000010000001101111001111 (
b111000010111111000000001100001 '
b1001110100110011111100110011000 &
b11111010111111000000000001111 %
b1001001010000000111111000111100 $
b10111001100111110000010110011100 #
1"
#106
0"
#107
b1001010 !
b1001010 +
b11111101001111110000111100111100 *
b11111110100011100100000111100000 )
b11111010000100000011011110011110 (
b1110000101111110000000011000011 '
b10011101001100111111001100110000 &
b111110101111110000000000011111 %
b10010010100000001111110001111000 $
b1110011001111100000101100111001 #
1"
#108
0"
#109
b11010011 !
b11010011 +
b11111010011111100001111001111000 *
b11111101000111001000001111000000 )
b11110100001000000110111100111100 (
b11100001011111100000000110000111 '
b111010011001111110011001100001 &
b1111101011111100000000000111111 %
b100101000000011111100011110000 $
b11100110011111000001011001110011 #
1"
#110
0"
#111
b11110101 !
b11110101 +
b11110100111111000011110011110000 *
b11111010001110010000011110000000 )
b11101000010000001101111001111001 (
b11000010111111000000001100001111 '
b1110100110011111100110011000011 &
b11111010111111000000000001111110 %
b1001010000000111111000111100000 $
b11001100111110000010110011100111 #
1"
#112
0"
#113
b11100101 !
b11100101 +
b11101001111110000111100111100001 *
b11110100011100100000111100000000 )
b11010000100000011011110011110010 (
b10000101111110000000011000011111 '
b11101001100111111001100110000111 &
b11110101111110000000000011111100 %
b10010100000001111110001111000000 $
b10011001111100000101100111001110 #
1"
#114
0"
#115
b100101 !
b100101 +
b11010011111100001111001111000010 *
b11101000111001000001111000000001 )
b10100001000000110111100111100101 (
b1011111100000000110000111110 '
b11010011001111110011001100001110 &
b11101011111100000000000111111001 %
b101000000011111100011110000000 $
b110011111000001011001110011101 #
1"
#116
0"
#117
b101100 !
b101100 +
b10100111111000011110011110000101 *
b11010001110010000011110000000010 )
b1000010000001101111001111001010 (
b10111111000000001100001111101 '
b10100110011111100110011000011101 &
b11010111111000000000001111110010 %
b1010000000111111000111100000001 $
b1100111110000010110011100111010 #
1"
#118
0"
#119
b10101000 !
b10101000 +
b1001111110000111100111100001010 *
b10100011100100000111100000000101 )
b10000100000011011110011110010101 (
b101111110000000011000011111010 '
b1001100111111001100110000111010 &
b10101111110000000000011111100101 %
b10100000001111110001111000000011 $
b11001111100000101100111001110101 #
1"
#120
0"
#121
b10111000 !
b10111000 +
b10011111100001111001111000010100 *
b1000111001000001111000000001010 )
b1000000110111100111100101010 (
b1011111100000000110000111110101 '
b10011001111110011001100001110100 &
b1011111100000000000111111001011 %
b1000000011111100011110000000110 $
b10011111000001011001110011101010 #
1"
#122
0"
#123
b10011100 !
b10011100 +
b111111000011110011110000101001 *
b10001110010000011110000000010101 )
b10000001101111001111001010101 (
b10111111000000001100001111101010 '
b110011111100110011000011101001 &
b10111111000000000001111110010110 %
b10000000111111000111100000001101 $
b111110000010110011100111010101 #
1"
#124
0"
#125
b11001 !
b11001 +
b1111110000111100111100001010011 *
b11100100000111100000000101011 )
b100000011011110011110010101010 (
b1111110000000011000011111010101 '
b1100111111001100110000111010010 &
b1111110000000000011111100101101 %
b1111110001111000000011010 $
b1111100000101100111001110101011 #
1"
#126
0"
#127
b10100110 !
b10100110 +
b11111100001111001111000010100110 *
b111001000001111000000001010111 )
b1000000110111100111100101010100 (
b11111100000000110000111110101010 '
b11001111110011001100001110100101 &
b11111100000000000111111001011010 %
b11111100011110000000110100 $
b11111000001011001110011101010110 #
1"
#128
0"
#129
b1011001 !
b1011001 +
b11111000011110011110000101001100 *
b1110010000011110000000010101111 )
b10000001101111001111001010101001 (
b11111000000001100001111101010100 '
b10011111100110011000011101001010 &
b11111000000000001111110010110100 %
b111111000111100000001101000 $
b11110000010110011100111010101100 #
1"
#130
0"
#131
b11100110 !
b11100110 +
b11110000111100111100001010011000 *
b11100100000111100000000101011111 )
b11011110011110010101010010 (
b11110000000011000011111010101000 '
b111111001100110000111010010101 &
b11110000000000011111100101101000 %
b1111110001111000000011010000 $
b11100000101100111001110101011001 #
1"
#132
0"
#133
b101000 !
b101000 +
b11100001111001111000010100110001 *
b11001000001111000000001010111111 )
b110111100111100101010100100 (
b11100000000110000111110101010001 '
b1111110011001100001110100101011 &
b11100000000000111111001011010001 %
b11111100011110000000110100001 $
b11000001011001110011101010110011 #
1"
#134
0"
#135
b11010111 !
b11010111 +
b11000011110011110000101001100011 *
b10010000011110000000010101111110 )
b1101111001111001010101001000 (
b11000000001100001111101010100011 '
b11111100110011000011101001010110 &
b11000000000001111110010110100011 %
b111111000111100000001101000011 $
b10000010110011100111010101100111 #
1"
#136
0"
#137
b10101011 !
b10101011 +
b10000111100111100001010011000111 *
b100000111100000000101011111100 )
b11011110011110010101010010001 (
b10000000011000011111010101000111 '
b11111001100110000111010010101100 &
b10000000000011111100101101000111 %
b1111110001111000000011010000111 $
b101100111001110101011001110 #
1"
#138
0"
#139
b10010 !
b10010 +
b1111001111000010100110001110 *
b1000001111000000001010111111000 )
b110111100111100101010100100011 (
b110000111110101010001110 '
b11110011001100001110100101011000 &
b111111001011010001110 %
b11111100011110000000110100001110 $
b1011001110011101010110011100 #
1"
#140
0"
#141
b110 !
b110 +
b11110011110000101001100011101 *
b10000011110000000010101111110001 )
b1101111001111001010101001000110 (
b1100001111101010100011100 '
b11100110011000011101001010110001 &
b1111110010110100011100 %
b11111000111100000001101000011100 $
b10110011100111010101100111001 #
1"
#142
0"
#143
b10010010 !
b10010010 +
b111100111100001010011000111011 *
b111100000000101011111100010 )
b11011110011110010101010010001100 (
b11000011111010101000111000 '
b11001100110000111010010101100011 &
b11111100101101000111000 %
b11110001111000000011010000111000 $
b101100111001110101011001110010 #
1"
#144
0"
#145
b11111011 !
b11111011 +
b1111001111000010100110001110111 *
b1111000000001010111111000100 )
b10111100111100101010100100011000 (
b110000111110101010001110000 '
b10011001100001110100101011000110 &
b111111001011010001110000 %
b11100011110000000110100001110001 $
b1011001110011101010110011100101 #
1"
#146
0"
#147
b11101001 !
b11101001 +
b11110011110000101001100011101110 *
b11110000000010101111110001001 )
b1111001111001010101001000110001 (
b1100001111101010100011100000 '
b110011000011101001010110001101 &
b1111110010110100011100000 %
b11000111100000001101000011100011 $
b10110011100111010101100111001010 #
1"
#148
0"
#149
b1101101 !
b1101101 +
b11100111100001010011000111011101 *
b111100000000101011111100010011 )
b11110011110010101010010001100010 (
b11000011111010101000111000001 '
b1100110000111010010101100011010 &
b11111100101101000111000000 %
b10001111000000011010000111000111 $
b1100111001110101011001110010100 #
1"
#150
0"
#151
b100 !
b100 +
b11001111000010100110001110111011 *
b1111000000001010111111000100111 )
b11100111100101010100100011000101 (
b110000111110101010001110000011 '
b11001100001110100101011000110101 &
b111111001011010001110000000 %
b11110000000110100001110001111 $
b11001110011101010110011100101001 #
1"
#152
0"
#153
b10010011 !
b10010011 +
b10011110000101001100011101110110 *
b11110000000010101111110001001110 )
b11001111001010101001000110001011 (
b1100001111101010100011100000110 '
b10011000011101001010110001101010 &
b1111110010110100011100000000 %
b111100000001101000011100011111 $
b10011100111010101100111001010010 #
1"
#154
0"
#155
b10001 !
b10001 +
b111100001010011000111011101101 *
b11100000000101011111100010011101 )
b10011110010101010010001100010110 (
b11000011111010101000111000001101 '
b110000111010010101100011010101 &
b11111100101101000111000000001 %
b1111000000011010000111000111111 $
b111001110101011001110010100101 #
1"
#156
0"
#157
b11000001 !
b11000001 +
b1111000010100110001110111011011 *
b11000000001010111111000100111011 )
b111100101010100100011000101101 (
b10000111110101010001110000011011 '
b1100001110100101011000110101010 &
b111111001011010001110000000011 %
b11110000000110100001110001111110 $
b1110011101010110011100101001011 #
1"
#158
0"
#159
b1010110 !
b1010110 +
b11110000101001100011101110110110 *
b10000000010101111110001001110111 )
b1111001010101001000110001011011 (
b1111101010100011100000110110 '
b11000011101001010110001101010101 &
b1111110010110100011100000000111 %
b11100000001101000011100011111101 $
b11100111010101100111001010010111 #
1"
#160
0"
#161
b1001011 !
b1001011 +
b11100001010011000111011101101101 *
b101011111100010011101110 )
b11110010101010010001100010110110 (
b11111010101000111000001101101 '
b10000111010010101100011010101011 &
b11111100101101000111000000001110 %
b11000000011010000111000111111011 $
b11001110101011001110010100101111 #
1"
#162
0"
#163
b11011111 !
b11011111 +
b11000010100110001110111011011011 *
b1010111111000100111011100 )
b11100101010100100011000101101101 (
b111110101010001110000011011011 '
b1110100101011000110101010110 &
b11111001011010001110000000011100 %
b10000000110100001110001111110111 $
b10011101010110011100101001011110 #
1"
#164
0"
#165
b1000100 !
b1000100 +
b10000101001100011101110110110111 *
b10101111110001001110111000 )
b11001010101001000110001011011011 (
b1111101010100011100000110110111 '
b11101001010110001101010101101 &
b11110010110100011100000000111000 %
b1101000011100011111101110 $
b111010101100111001010010111101 #
1"
#166
0"
#167
b11111011 !
b11111011 +
b1010011000111011101101101110 *
b101011111100010011101110000 )
b10010101010010001100010110110110 (
b11111010101000111000001101101110 '
b111010010101100011010101011011 &
b11100101101000111000000001110001 %
b11010000111000111111011100 $
b1110101011001110010100101111011 #
1"
#168
0"
#169
b10101111 !
b10101111 +
b10100110001110111011011011101 *
b1010111111000100111011100000 )
b101010100100011000101101101100 (
b11110101010001110000011011011100 '
b1110100101011000110101010110111 &
b11001011010001110000000011100011 %
b110100001110001111110111000 $
b11101010110011100101001011110111 #
1"
#170
0"
#171
b11110110 !
b11110110 +
b101001100011101110110110111010 *
b10101111110001001110111000001 )
b1010101001000110001011011011001 (
b11101010100011100000110110111001 '
b11101001010110001101010101101111 &
b10010110100011100000000111000110 %
b1101000011100011111101110000 $
b11010101100111001010010111101110 #
1"
#172
0"
#173
b11011001 !
b11011001 +
b1010011000111011101101101110101 *
b101011111100010011101110000010 )
b10101010010001100010110110110011 (
b11010101000111000001101101110010 '
b11010010101100011010101011011110 &
b101101000111000000001110001100 %
b11010000111000111111011100001 $
b10101011001110010100101111011101 #
1"
#174
0"
#175
b1001101 !
b1001101 +
b10100110001110111011011011101011 *
b1010111111000100111011100000101 )
b1010100100011000101101101100111 (
b10101010001110000011011011100101 '
b10100101011000110101010110111101 &
b1011010001110000000011100011001 %
b110100001110001111110111000011 $
b1010110011100101001011110111011 #
1"
#176
0"
#177
b10011101 !
b10011101 +
b1001100011101110110110111010110 *
b10101111110001001110111000001011 )
b10101001000110001011011011001111 (
b1010100011100000110110111001011 '
b1001010110001101010101101111010 &
b10110100011100000000111000110010 %
b1101000011100011111101110000110 $
b10101100111001010010111101110111 #
1"
#178
0"
#179
b10110000 !
b10110000 +
b10011000111011101101101110101100 *
b1011111100010011101110000010111 )
b1010010001100010110110110011111 (
b10101000111000001101101110010111 '
b10010101100011010101011011110100 &
b1101000111000000001110001100100 %
b11010000111000111111011100001100 $
b1011001110010100101111011101111 #
1"
#180
0"
#181
b10110001 !
b10110001 +
b110001110111011011011101011001 *
b10111111000100111011100000101110 )
b10100100011000101101101100111111 (
b1010001110000011011011100101111 '
b101011000110101010110111101000 &
b11010001110000000011100011001000 %
b10100001110001111110111000011001 $
b10110011100101001011110111011110 #
1"
#182
0"
#183
b11110 !
b11110 +
b1100011101110110110111010110010 *
b1111110001001110111000001011101 )
b1001000110001011011011001111110 (
b10100011100000110110111001011111 '
b1010110001101010101101111010001 &
b10100011100000000111000110010001 %
b1000011100011111101110000110010 $
b1100111001010010111101110111100 #
1"
#184
0"
#185
b11000101 !
b11000101 +
b11000111011101101101110101100101 *
b11111100010011101110000010111010 )
b10010001100010110110110011111100 (
b1000111000001101101110010111110 '
b10101100011010101011011110100011 &
b1000111000000001110001100100010 %
b10000111000111111011100001100101 $
b11001110010100101111011101111001 #
1"
#186
0"
#187
b11111111 !
b11111111 +
b10001110111011011011101011001011 *
b11111000100111011100000101110100 )
b100011000101101101100111111000 (
b10001110000011011011100101111101 '
b1011000110101010110111101000111 &
b10001110000000011100011001000101 %
b1110001111110111000011001010 $
b10011100101001011110111011110010 #
1"
#188
0"
#189
b10001110 !
b10001110 +
b11101110110110111010110010111 *
b11110001001110111000001011101000 )
b1000110001011011011001111110000 (
b11100000110110111001011111011 '
b10110001101010101101111010001110 &
b11100000000111000110010001011 %
b11100011111101110000110010101 $
b111001010010111101110111100101 #
1"
#190
0"
