modules/note2dds.v
module note2dds(CLK, NOTE, ADDER);

input wire CLK;
input wire [6:0] NOTE;
output [31:0] ADDER;

reg [31:0] ADDER_tbl [15:0];
reg [3:0] addr;
reg [3:0] divider;

// note div 12 ( * 0,08333333333333333333333333333333)
//; Add input / 16 to accumulator
//; Add input / 64 to accumulator

initial begin
   addr <= 4'd0;
	divider <= 4'd0;
	ADDER_tbl[ 4'd0] <= 32'd0359575;
	ADDER_tbl[ 4'd1] <= 32'd0380957;
	ADDER_tbl[ 4'd2] <= 32'd0403610;
	ADDER_tbl[ 4'd3] <= 32'd0427610;
	ADDER_tbl[ 4'd4] <= 32'd0453037;
	ADDER_tbl[ 4'd5] <= 32'd0479976;
	ADDER_tbl[ 4'd6] <= 32'd0508516;
	ADDER_tbl[ 4'd7] <= 32'd0538754;
	ADDER_tbl[ 4'd8] <= 32'd0570790;
	ADDER_tbl[ 4'd9] <= 32'd0604731;
	ADDER_tbl[4'd10] <= 32'd0640691;
	ADDER_tbl[4'd11] <= 32'd0678788;
	ADDER_tbl[4'd12] <= 32'd0;
	ADDER_tbl[4'd13] <= 32'd0;
	ADDER_tbl[4'd14] <= 32'd0;
	ADDER_tbl[4'd15] <= 32'd0;
end

assign ADDER = ADDER_tbl[addr] >> divider;


wire [6:0] note_a = (NOTE <  12) ? NOTE :
					     (NOTE <  24) ? NOTE - 7'd012 :
					     (NOTE <  36) ? NOTE - 7'd024 :
					     (NOTE <  48) ? NOTE - 7'd036 :
					     (NOTE <  60) ? NOTE - 7'd048 :
					     (NOTE <  72) ? NOTE - 7'd060 :
					     (NOTE <  84) ? NOTE - 7'd072 :
					     (NOTE <  96) ? NOTE - 7'd084 :
					     (NOTE < 108) ? NOTE - 7'd096 :
					     (NOTE < 120) ? NOTE - 7'd0108 : NOTE - 7'd0120 ;

wire [3:0] div_val = (NOTE <  12) ? 4'd010 :
					     (NOTE <  24) ? 4'd09 :
					     (NOTE <  36) ? 4'd08 :
					     (NOTE <  48) ? 4'd07 :
					     (NOTE <  60) ? 4'd06 :
					     (NOTE <  72) ? 4'd05 :
					     (NOTE <  84) ? 4'd04 :
					     (NOTE <  96) ? 4'd03 :
					     (NOTE < 108) ? 4'd02 :
					     (NOTE < 120) ? 4'd01 : 4'd00 ;

						  
always @ (posedge CLK) begin
	addr <= note_a[3:0];
	divider <= div_val;
end

endmodule

trunk/benches/note2dds/testbench.v
module testbench();

reg [6:0] in_val; //7 bit
reg tb_clk;

wire [31:0] ADDER;
note2dds dds_adder(tb_clk, in_val, ADDER);

// note div 12 ( * 0,08333333333333333333333333333333)
//; Add input / 16 to accumulator >>>  4
//; Add input / 64 to accumulator >>>  6
//; Add input / 256 to accumulator >>> 8
//; Add input / 1024 to accumulator >>> 10
//муть, проще сделать case

wire [3:0] x_div12 = (in_val <  12) ? 0 :
					 (in_val <  24) ? 1 :
					 (in_val <  36) ? 2 :
					 (in_val <  48) ? 3 :
					 (in_val <  60) ? 4 :
					 (in_val <  72) ? 5 :
					 (in_val <  84) ? 6 :
					 (in_val <  96) ? 7 :
					 (in_val < 108) ? 8 :
					 (in_val < 120) ? 9 : 10 ;

initial
begin
    $dumpfile("bench.vcd");
    $dumpvars(0,testbench);

    $display("starting testbench!!!!");

	in_val = 0;
	
	repeat (128) begin
		#20;
		$display("in=", in_val, " div 12 = ", x_div12, " mod12 = ", );

		in_val = in_val + 1'b1;		
	end
	
    $display("finished OK!");
    $finish;
end
	
initial
begin
	tb_clk <= 0;
	repeat (200000) begin
		#1;
		tb_clk <= 1;
		#1;
		tb_clk <= 0;
	end
end	
	
endmodule

benches/note2dds/bench.vcd
$date
	Wed Nov 12 03:51:01 2014
$end
$version
	Icarus Verilog
$end
$timescale
	1s
$end
$scope module testbench $end
$var wire 4 ! x_div12 [3:0] $end
$var wire 32 " ADDER [31:0] $end
$var reg 7 # in_val [6:0] $end
$var reg 1 $ tb_clk $end
$scope module dds_adder $end
$var wire 1 $ CLK $end
$var wire 7 % NOTE [6:0] $end
$var wire 7 & note_a [6:0] $end
$var wire 4 ' div_val [3:0] $end
$var wire 32 ( ADDER [31:0] $end
$var reg 4 ) addr [3:0] $end
$var reg 4 * divider [3:0] $end
$upscope $end
$upscope $end
$enddefinitions $end
#0
$dumpvars
b0 *
b0 )
b1010111110010010111 (
b1010 '
b0 &
b0 %
0$
b0 #
b1010111110010010111 "
b0 !
$end
#1
b101011111 "
b101011111 (
b1010 *
1$
#2
0$
#3
1$
#4
0$
#5
1$
#6
0$
#7
1$
#8
0$
#9
1$
#10
0$
#11
1$
#12
0$
#13
1$
#14
0$
#15
1$
#16
0$
#17
1$
#18
0$
#19
1$
#20
0$
b1 &
b1 #
b1 %
#21
b101110100 "
b101110100 (
b1 )
1$
#22
0$
#23
1$
#24
0$
#25
1$
#26
0$
#27
1$
#28
0$
#29
1$
#30
0$
#31
1$
#32
0$
#33
1$
#34
0$
#35
1$
#36
0$
#37
1$
#38
0$
#39
1$
#40
0$
b10 &
b10 #
b10 %
#41
b110001010 "
b110001010 (
b10 )
1$
#42
0$
#43
1$
#44
0$
#45
1$
#46
0$
#47
1$
#48
0$
#49
1$
#50
0$
#51
1$
#52
0$
#53
1$
#54
0$
#55
1$
#56
0$
#57
1$
#58
0$
#59
1$
#60
0$
b11 &
b11 #
b11 %
#61
b110100001 "
b110100001 (
b11 )
1$
#62
0$
#63
1$
#64
0$
#65
1$
#66
0$
#67
1$
#68
0$
#69
1$
#70
0$
#71
1$
#72
0$
#73
1$
#74
0$
#75
1$
#76
0$
#77
1$
#78
0$
#79
1$
#80
0$
b100 &
b100 #
b100 %
#81
b110111010 "
b110111010 (
b100 )
1$
#82
0$
#83
1$
#84
0$
#85
1$
#86
0$
#87
1$
#88
0$
#89
1$
#90
0$
#91
1$
#92
0$
#93
1$
#94
0$
#95
1$
#96
0$
#97
1$
#98
0$
#99
1$
#100
0$
b101 &
b101 #
b101 %
#101
b111010100 "
b111010100 (
b101 )
1$
#102
0$
#103
1$
#104
0$
#105
1$
#106
0$
#107
1$
#108
0$
#109
1$
#110
0$
#111
1$
#112
0$
#113
1$
#114
0$
#115
1$
#116
0$
#117
1$
#118
0$
#119
1$
#120
0$
b110 &
b110 #
b110 %
#121
b111110000 "
b111110000 (
b110 )
1$
#122
0$
#123
1$
#124
0$
#125
1$
#126
0$
#127
1$
#128
0$
#129
1$
#130
0$
#131
1$
#132
0$
#133
1$
#134
0$
#135
1$
#136
0$
#137
1$
#138
0$
#139
1$
#140
0$
b111 &
b111 #
b111 %
#141
b1000001110 "
b1000001110 (
b111 )
1$
#142
0$
#143
1$
#144
0$
#145
1$
#146
0$
#147
1$
#148
0$
#149
1$
#150
0$
#151
1$
#152
0$
#153
1$
#154
0$
#155
1$
#156
0$
#157
1$
#158
0$
#159
1$
#160
0$
b1000 &
b1000 #
b1000 %
#161
b1000101101 "
b1000101101 (
b1000 )
1$
#162
0$
#163
1$
#164
0$
#165
1$
#166
0$
#167
1$
#168
0$
#169
1$
#170
0$
#171
1$
#172
0$
#173
1$
#174
0$
#175
1$
#176
0$
#177
1$
#178
0$
#179
1$
#180
0$
b1001 &
b1001 #
b1001 %
#181
b1001001110 "
b1001001110 (
b1001 )
1$
#182
0$
#183
1$
#184
0$
#185
1$
#186
0$
#187
1$
#188
0$
#189
1$
#190
0$
#191
1$
#192
0$
#193
1$
#194
0$
#195
1$
#196
0$
#197
1$
#198
0$
#199
1$
#200
0$
b1010 &
b1010 #
b1010 %
#201
b1001110001 "
b1001110001 (
b1010 )
1$
#202
0$
#203
1$
#204
0$
#205
1$
#206
0$
#207
1$
#208
0$
#209
1$
#210
0$
#211
1$
#212
0$
#213
1$
#214
0$
#215
1$
#216
0$
#217
1$
#218
0$
#219
1$
#220
0$
b1011 &
b1011 #
b1011 %
#221
b1010010110 "
b1010010110 (
b1011 )
1$
#222
0$
#223
1$
#224
0$
#225
1$
#226
0$
#227
1$
#228
0$
#229
1$
#230
0$
#231
1$
#232
0$
#233
1$
#234
0$
#235
1$
#236
0$
#237
1$
#238
0$
#239
1$
#240
0$
b1 !
b0 &
b1001 '
b1100 #
b1100 %
#241
b1001 *
b1010111110 "
b1010111110 (
b0 )
1$
#242
0$
#243
1$
#244
0$
#245
1$
#246
0$
#247
1$
#248
0$
#249
1$
#250
0$
#251
1$
#252
0$
#253
1$
#254
0$
#255
1$
#256
0$
#257
1$
#258
0$
#259
1$
#260
0$
b1 &
b1101 #
b1101 %
#261
b1011101000 "
b1011101000 (
b1 )
1$
#262
0$
#263
1$
#264
0$
#265
1$
#266
0$
#267
1$
#268
0$
#269
1$
#270
0$
#271
1$
#272
0$
#273
1$
#274
0$
#275
1$
#276
0$
#277
1$
#278
0$
#279
1$
#280
0$
b10 &
b1110 #
b1110 %
#281
b1100010100 "
b1100010100 (
b10 )
1$
#282
0$
#283
1$
#284
0$
#285
1$
#286
0$
#287
1$
#288
0$
#289
1$
#290
0$
#291
1$
#292
0$
#293
1$
#294
0$
#295
1$
#296
0$
#297
1$
#298
0$
#299
1$
#300
0$
b11 &
b1111 #
b1111 %
#301
b1101000011 "
b1101000011 (
b11 )
1$
#302
0$
#303
1$
#304
0$
#305
1$
#306
0$
#307
1$
#308
0$
#309
1$
#310
0$
#311
1$
#312
0$
#313
1$
#314
0$
#315
1$
#316
0$
#317
1$
#318
0$
#319
1$
#320
0$
b100 &
b10000 #
b10000 %
#321
b1101110100 "
b1101110100 (
b100 )
1$
#322
0$
#323
1$
#324
0$
#325
1$
#326
0$
#327
1$
#328
0$
#329
1$
#330
0$
#331
1$
#332
0$
#333
1$
#334
0$
#335
1$
#336
0$
#337
1$
#338
0$
#339
1$
#340
0$
b101 &
b10001 #
b10001 %
#341
b1110101001 "
b1110101001 (
b101 )
1$
#342
0$
#343
1$
#344
0$
#345
1$
#346
0$
#347
1$
#348
0$
#349
1$
#350
0$
#351
1$
#352
0$
#353
1$
#354
0$
#355
1$
#356
0$
#357
1$
#358
0$
#359
1$
#360
0$
b110 &
b10010 #
b10010 %
#361
b1111100001 "
b1111100001 (
b110 )
1$
#362
0$
#363
1$
#364
0$
#365
1$
#366
0$
#367
1$
#368
0$
#369
1$
#370
0$
#371
1$
#372
0$
#373
1$
#374
0$
#375
1$
#376
0$
#377
1$
#378
0$
#379
1$
#380
0$
b111 &
b10011 #
b10011 %
#381
b10000011100 "
b10000011100 (
b111 )
1$
#382
0$
#383
1$
#384
0$
#385
1$
#386
0$
#387
1$
#388
0$
#389
1$
#390
0$
#391
1$
#392
0$
#393
1$
#394
0$
#395
1$
#396
0$
#397
1$
#398
0$
#399
1$
#400
0$
b1000 &
b10100 #
b10100 %
#401
b10001011010 "
b10001011010 (
b1000 )
1$
#402
0$
#403
1$
#404
0$
#405
1$
#406
0$
#407
1$
#408
0$
#409
1$
#410
0$
#411
1$
#412
0$
#413
1$
#414
0$
#415
1$
#416
0$
#417
1$
#418
0$
#419
1$
#420
0$
b1001 &
b10101 #
b10101 %
#421
b10010011101 "
b10010011101 (
b1001 )
1$
#422
0$
#423
1$
#424
0$
#425
1$
#426
0$
#427
1$
#428
0$
#429
1$
#430
0$
#431
1$
#432
0$
#433
1$
#434
0$
#435
1$
#436
0$
#437
1$
#438
0$
#439
1$
#440
0$
b1010 &
b10110 #
b10110 %
#441
b10011100011 "
b10011100011 (
b1010 )
1$
#442
0$
#443
1$
#444
0$
#445
1$
#446
0$
#447
1$
#448
0$
#449
1$
#450
0$
#451
1$
#452
0$
#453
1$
#454
0$
#455
1$
#456
0$
#457
1$
#458
0$
#459
1$
#460
0$
b1011 &
b10111 #
b10111 %
#461
b10100101101 "
b10100101101 (
b1011 )
1$
#462
0$
#463
1$
#464
0$
#465
1$
#466
0$
#467
1$
#468
0$
#469
1$
#470
0$
#471
1$
#472
0$
#473
1$
#474
0$
#475
1$
#476
0$
#477
1$
#478
0$
#479
1$
#480
0$
b10 !
b0 &
b1000 '
b11000 #
b11000 %
#481
b1000 *
b10101111100 "
b10101111100 (
b0 )
1$
#482
0$
#483
1$
#484
0$
#485
1$
#486
0$
#487
1$
#488
0$
#489
1$
#490
0$
#491
1$
#492
0$
#493
1$
#494
0$
#495
1$
#496
0$
#497
1$
#498
0$
#499
1$
#500
0$
b1 &
b11001 #
b11001 %
#501
b10111010000 "
b10111010000 (
b1 )
1$
#502
0$
#503
1$
#504
0$
#505
1$
#506
0$
#507
1$
#508
0$
#509
1$
#510
0$
#511
1$
#512
0$
#513
1$
#514
0$
#515
1$
#516
0$
#517
1$
#518
0$
#519
1$
#520
0$
b10 &
b11010 #
b11010 %
#521
b11000101000 "
b11000101000 (
b10 )
1$
#522
0$
#523
1$
#524
0$
#525
1$
#526
0$
#527
1$
#528
0$
#529
1$
#530
0$
#531
1$
#532
0$
#533
1$
#534
0$
#535
1$
#536
0$
#537
1$
#538
0$
#539
1$
#540
0$
b11 &
b11011 #
b11011 %
#541
b11010000110 "
b11010000110 (
b11 )
1$
#542
0$
#543
1$
#544
0$
#545
1$
#546
0$
#547
1$
#548
0$
#549
1$
#550
0$
#551
1$
#552
0$
#553
1$
#554
0$
#555
1$
#556
0$
#557
1$
#558
0$
#559
1$
#560
0$
b100 &
b11100 #
b11100 %
#561
b11011101001 "
b11011101001 (
b100 )
1$
#562
0$
#563
1$
#564
0$
#565
1$
#566
0$
#567
1$
#568
0$
#569
1$
#570
0$
#571
1$
#572
0$
#573
1$
#574
0$
#575
1$
#576
0$
#577
1$
#578
0$
#579
1$
#580
0$
b101 &
b11101 #
b11101 %
#581
b11101010010 "
b11101010010 (
b101 )
1$
#582
0$
#583
1$
#584
0$
#585
1$
#586
0$
#587
1$
#588
0$
#589
1$
#590
0$
#591
1$
#592
0$
#593
1$
#594
0$
#595
1$
#596
0$
#597
1$
#598
0$
#599
1$
#600
0$
b110 &
b11110 #
b11110 %
#601
b11111000010 "
b11111000010 (
b110 )
1$
#602
0$
#603
1$
#604
0$
#605
1$
#606
0$
#607
1$
#608
0$
#609
1$
#610
0$
#611
1$
#612
0$
#613
1$
#614
0$
#615
1$
#616
0$
#617
1$
#618
0$
#619
1$
#620
0$
b111 &
b11111 #
b11111 %
#621
b100000111000 "
b100000111000 (
b111 )
1$
#622
0$
#623
1$
#624
0$
#625
1$
#626
0$
#627
1$
#628
0$
#629
1$
#630
0$
#631
1$
#632
0$
#633
1$
#634
0$
#635
1$
#636
0$
#637
1$
#638
0$
#639
1$
#640
0$
b1000 &
b100000 #
b100000 %
#641
b100010110101 "
b100010110101 (
b1000 )
1$
#642
0$
#643
1$
#644
0$
#645
1$
#646
0$
#647
1$
#648
0$
#649
1$
#650
0$
#651
1$
#652
0$
#653
1$
#654
0$
#655
1$
#656
0$
#657
1$
#658
0$
#659
1$
#660
0$
b1001 &
b100001 #
b100001 %
#661
b100100111010 "
b100100111010 (
b1001 )
1$
#662
0$
#663
1$
#664
0$
#665
1$
#666
0$
#667
1$
#668
0$
#669
1$
#670
0$
#671
1$
#672
0$
#673
1$
#674
0$
#675
1$
#676
0$
#677
1$
#678
0$
#679
1$
#680
0$
b1010 &
b100010 #
b100010 %
#681
b100111000110 "
b100111000110 (
b1010 )
1$
#682
0$
#683
1$
#684
0$
#685
1$
#686
0$
#687
1$
#688
0$
#689
1$
#690
0$
#691
1$
#692
0$
#693
1$
#694
0$
#695
1$
#696
0$
#697
1$
#698
0$
#699
1$
#700
0$
b1011 &
b100011 #
b100011 %
#701
b101001011011 "
b101001011011 (
b1011 )
1$
#702
0$
#703
1$
#704
0$
#705
1$
#706
0$
#707
1$
#708
0$
#709
1$
#710
0$
#711
1$
#712
0$
#713
1$
#714
0$
#715
1$
#716
0$
#717
1$
#718
0$
#719
1$
#720
0$
b11 !
b0 &
b111 '
b100100 #
b100100 %
#721
b111 *
b101011111001 "
b101011111001 (
b0 )
1$
#722
0$
#723
1$
#724
0$
#725
1$
#726
0$
#727
1$
#728
0$
#729
1$
#730
0$
#731
1$
#732
0$
#733
1$
#734
0$
#735
1$
#736
0$
#737
1$
#738
0$
#739
1$
#740
0$
b1 &
b100101 #
b100101 %
#741
b101110100000 "
b101110100000 (
b1 )
1$
#742
0$
#743
1$
#744
0$
#745
1$
#746
0$
#747
1$
#748
0$
#749
1$
#750
0$
#751
1$
#752
0$
#753
1$
#754
0$
#755
1$
#756
0$
#757
1$
#758
0$
#759
1$
#760
0$
b10 &
b100110 #
b100110 %
#761
b110001010001 "
b110001010001 (
b10 )
1$
#762
0$
#763
1$
#764
0$
#765
1$
#766
0$
#767
1$
#768
0$
#769
1$
#770
0$
#771
1$
#772
0$
#773
1$
#774
0$
#775
1$
#776
0$
#777
1$
#778
0$
#779
1$
#780
0$
b11 &
b100111 #
b100111 %
#781
b110100001100 "
b110100001100 (
b11 )
1$
#782
0$
#783
1$
#784
0$
#785
1$
#786
0$
#787
1$
#788
0$
#789
1$
#790
0$
#791
1$
#792
0$
#793
1$
#794
0$
#795
1$
#796
0$
#797
1$
#798
0$
#799
1$
#800
0$
b100 &
b101000 #
b101000 %
#801
b110111010011 "
b110111010011 (
b100 )
1$
#802
0$
#803
1$
#804
0$
#805
1$
#806
0$
#807
1$
#808
0$
#809
1$
#810
0$
#811
1$
#812
0$
#813
1$
#814
0$
#815
1$
#816
0$
#817
1$
#818
0$
#819
1$
#820
0$
b101 &
b101001 #
b101001 %
#821
b111010100101 "
b111010100101 (
b101 )
1$
#822
0$
#823
1$
#824
0$
#825
1$
#826
0$
#827
1$
#828
0$
#829
1$
#830
0$
#831
1$
#832
0$
#833
1$
#834
0$
#835
1$
#836
0$
#837
1$
#838
0$
#839
1$
#840
0$
b110 &
b101010 #
b101010 %
#841
b111110000100 "
b111110000100 (
b110 )
1$
#842
0$
#843
1$
#844
0$
#845
1$
#846
0$
#847
1$
#848
0$
#849
1$
#850
0$
#851
1$
#852
0$
#853
1$
#854
0$
#855
1$
#856
0$
#857
1$
#858
0$
#859
1$
#860
0$
b111 &
b101011 #
b101011 %
#861
b1000001110001 "
b1000001110001 (
b111 )
1$
#862
0$
#863
1$
#864
0$
#865
1$
#866
0$
#867
1$
#868
0$
#869
1$
#870
0$
#871
1$
#872
0$
#873
1$
#874
0$
#875
1$
#876
0$
#877
1$
#878
0$
#879
1$
#880
0$
b1000 &
b101100 #
b101100 %
#881
b1000101101011 "
b1000101101011 (
b1000 )
1$
#882
0$
#883
1$
#884
0$
#885
1$
#886
0$
#887
1$
#888
0$
#889
1$
#890
0$
#891
1$
#892
0$
#893
1$
#894
0$
#895
1$
#896
0$
#897
1$
#898
0$
#899
1$
#900
0$
b1001 &
b101101 #
b101101 %
#901
b1001001110100 "
b1001001110100 (
b1001 )
1$
#902
0$
#903
1$
#904
0$
#905
1$
#906
0$
#907
1$
#908
0$
#909
1$
#910
0$
#911
1$
#912
0$
#913
1$
#914
0$
#915
1$
#916
0$
#917
1$
#918
0$
#919
1$
#920
0$
b1010 &
b101110 #
b101110 %
#921
b1001110001101 "
b1001110001101 (
b1010 )
1$
#922
0$
#923
1$
#924
0$
#925
1$
#926
0$
#927
1$
#928
0$
#929
1$
#930
0$
#931
1$
#932
0$
#933
1$
#934
0$
#935
1$
#936
0$
#937
1$
#938
0$
#939
1$
#940
0$
b1011 &
b101111 #
b101111 %
#941
b1010010110111 "
b1010010110111 (
b1011 )
1$
#942
0$
#943
1$
#944
0$
#945
1$
#946
0$
#947
1$
#948
0$
#949
1$
#950
0$
#951
1$
#952
0$
#953
1$
#954
0$
#955
1$
#956
0$
#957
1$
#958
0$
#959
1$
#960
0$
b100 !
b0 &
b110 '
b110000 #
b110000 %
#961
b110 *
b1010111110010 "
b1010111110010 (
b0 )
1$
#962
0$
#963
1$
#964
0$
#965
1$
#966
0$
#967
1$
#968
0$
#969
1$
#970
0$
#971
1$
#972
0$
#973
1$
#974
0$
#975
1$
#976
0$
#977
1$
#978
0$
#979
1$
#980
0$
b1 &
b110001 #
b110001 %
#981
b1011101000000 "
b1011101000000 (
b1 )
1$
#982
0$
#983
1$
#984
0$
#985
1$
#986
0$
#987
1$
#988
0$
#989
1$
#990
0$
#991
1$
#992
0$
#993
1$
#994
0$
#995
1$
#996
0$
#997
1$
#998
0$
#999
1$
#1000
0$
b10 &
b110010 #
b110010 %
#1001
b1100010100010 "
b1100010100010 (
b10 )
1$
#1002
0$
#1003
1$
#1004
0$
#1005
1$
#1006
0$
#1007
1$
#1008
0$
#1009
1$
#1010
0$
#1011
1$
#1012
0$
#1013
1$
#1014
0$
#1015
1$
#1016
0$
#1017
1$
#1018
0$
#1019
1$
#1020
0$
b11 &
b110011 #
b110011 %
#1021
b1101000011001 "
b1101000011001 (
b11 )
1$
#1022
0$
#1023
1$
#1024
0$
#1025
1$
#1026
0$
#1027
1$
#1028
0$
#1029
1$
#1030
0$
#1031
1$
#1032
0$
#1033
1$
#1034
0$
#1035
1$
#1036
0$
#1037
1$
#1038
0$
#1039
1$
#1040
0$
b100 &
b110100 #
b110100 %
#1041
b1101110100110 "
b1101110100110 (
b100 )
1$
#1042
0$
#1043
1$
#1044
0$
#1045
1$
#1046
0$
#1047
1$
#1048
0$
#1049
1$
#1050
0$
#1051
1$
#1052
0$
#1053
1$
#1054
0$
#1055
1$
#1056
0$
#1057
1$
#1058
0$
#1059
1$
#1060
0$
b101 &
b110101 #
b110101 %
#1061
b1110101001011 "
b1110101001011 (
b101 )
1$
#1062
0$
#1063
1$
#1064
0$
#1065
1$
#1066
0$
#1067
1$
#1068
0$
#1069
1$
#1070
0$
#1071
1$
#1072
0$
#1073
1$
#1074
0$
#1075
1$
#1076
0$
#1077
1$
#1078
0$
#1079
1$
#1080
0$
b110 &
b110110 #
b110110 %
#1081
b1111100001001 "
b1111100001001 (
b110 )
1$
#1082
0$
#1083
1$
#1084
0$
#1085
1$
#1086
0$
#1087
1$
#1088
0$
#1089
1$
#1090
0$
#1091
1$
#1092
0$
#1093
1$
#1094
0$
#1095
1$
#1096
0$
#1097
1$
#1098
0$
#1099
1$
#1100
0$
b111 &
b110111 #
b110111 %
#1101
b10000011100010 "
b10000011100010 (
b111 )
1$
#1102
0$
#1103
1$
#1104
0$
#1105
1$
#1106
0$
#1107
1$
#1108
0$
#1109
1$
#1110
0$
#1111
1$
#1112
0$
#1113
1$
#1114
0$
#1115
1$
#1116
0$
#1117
1$
#1118
0$
#1119
1$
#1120
0$
b1000 &
b111000 #
b111000 %
#1121
b10001011010110 "
b10001011010110 (
b1000 )
1$
#1122
0$
#1123
1$
#1124
0$
#1125
1$
#1126
0$
#1127
1$
#1128
0$
#1129
1$
#1130
0$
#1131
1$
#1132
0$
#1133
1$
#1134
0$
#1135
1$
#1136
0$
#1137
1$
#1138
0$
#1139
1$
#1140
0$
b1001 &
b111001 #
b111001 %
#1141
b10010011101000 "
b10010011101000 (
b1001 )
1$
#1142
0$
#1143
1$
#1144
0$
#1145
1$
#1146
0$
#1147
1$
#1148
0$
#1149
1$
#1150
0$
#1151
1$
#1152
0$
#1153
1$
#1154
0$
#1155
1$
#1156
0$
#1157
1$
#1158
0$
#1159
1$
#1160
0$
b1010 &
b111010 #
b111010 %
#1161
b10011100011010 "
b10011100011010 (
b1010 )
1$
#1162
0$
#1163
1$
#1164
0$
#1165
1$
#1166
0$
#1167
1$
#1168
0$
#1169
1$
#1170
0$
#1171
1$
#1172
0$
#1173
1$
#1174
0$
#1175
1$
#1176
0$
#1177
1$
#1178
0$
#1179
1$
#1180
0$
b1011 &
b111011 #
b111011 %
#1181
b10100101101110 "
b10100101101110 (
b1011 )
1$
#1182
0$
#1183
1$
#1184
0$
#1185
1$
#1186
0$
#1187
1$
#1188
0$
#1189
1$
#1190
0$
#1191
1$
#1192
0$
#1193
1$
#1194
0$
#1195
1$
#1196
0$
#1197
1$
#1198
0$
#1199
1$
#1200
0$
b101 !
b0 &
b101 '
b111100 #
b111100 %
#1201
b101 *
b10101111100100 "
b10101111100100 (
b0 )
1$
#1202
0$
#1203
1$
#1204
0$
#1205
1$
#1206
0$
#1207
1$
#1208
0$
#1209
1$
#1210
0$
#1211
1$
#1212
0$
#1213
1$
#1214
0$
#1215
1$
#1216
0$
#1217
1$
#1218
0$
#1219
1$
#1220
0$
b1 &
b111101 #
b111101 %
#1221
b10111010000000 "
b10111010000000 (
b1 )
1$
#1222
0$
#1223
1$
#1224
0$
#1225
1$
#1226
0$
#1227
1$
#1228
0$
#1229
1$
#1230
0$
#1231
1$
#1232
0$
#1233
1$
#1234
0$
#1235
1$
#1236
0$
#1237
1$
#1238
0$
#1239
1$
#1240
0$
b10 &
b111110 #
b111110 %
#1241
b11000101000100 "
b11000101000100 (
b10 )
1$
#1242
0$
#1243
1$
#1244
0$
#1245
1$
#1246
0$
#1247
1$
#1248
0$
#1249
1$
#1250
0$
#1251
1$
#1252
0$
#1253
1$
#1254
0$
#1255
1$
#1256
0$
#1257
1$
#1258
0$
#1259
1$
#1260
0$
b11 &
b111111 #
b111111 %
#1261
b11010000110010 "
b11010000110010 (
b11 )
1$
#1262
0$
#1263
1$
#1264
0$
#1265
1$
#1266
0$
#1267
1$
#1268
0$
#1269
1$
#1270
0$
#1271
1$
#1272
0$
#1273
1$
#1274
0$
#1275
1$
#1276
0$
#1277
1$
#1278
0$
#1279
1$
#1280
0$
b100 &
b1000000 #
b1000000 %
#1281
b11011101001101 "
b11011101001101 (
b100 )
1$
#1282
0$
#1283
1$
#1284
0$
#1285
1$
#1286
0$
#1287
1$
#1288
0$
#1289
1$
#1290
0$
#1291
1$
#1292
0$
#1293
1$
#1294
0$
#1295
1$
#1296
0$
#1297
1$
#1298
0$
#1299
1$
#1300
0$
b101 &
b1000001 #
b1000001 %
#1301
b11101010010111 "
b11101010010111 (
b101 )
1$
#1302
0$
#1303
1$
#1304
0$
#1305
1$
#1306
0$
#1307
1$
#1308
0$
#1309
1$
#1310
0$
#1311
1$
#1312
0$
#1313
1$
#1314
0$
#1315
1$
#1316
0$
#1317
1$
#1318
0$
#1319
1$
#1320
0$
b110 &
b1000010 #
b1000010 %
#1321
b11111000010011 "
b11111000010011 (
b110 )
1$
#1322
0$
#1323
1$
#1324
0$
#1325
1$
#1326
0$
#1327
1$
#1328
0$
#1329
1$
#1330
0$
#1331
1$
#1332
0$
#1333
1$
#1334
0$
#1335
1$
#1336
0$
#1337
1$
#1338
0$
#1339
1$
#1340
0$
b111 &
b1000011 #
b1000011 %
#1341
b100000111000100 "
b100000111000100 (
b111 )
1$
#1342
0$
#1343
1$
#1344
0$
#1345
1$
#1346
0$
#1347
1$
#1348
0$
#1349
1$
#1350
0$
#1351
1$
#1352
0$
#1353
1$
#1354
0$
#1355
1$
#1356
0$
#1357
1$
#1358
0$
#1359
1$
#1360
0$
b1000 &
b1000100 #
b1000100 %
#1361
b100010110101101 "
b100010110101101 (
b1000 )
1$
#1362
0$
#1363
1$
#1364
0$
#1365
1$
#1366
0$
#1367
1$
#1368
0$
#1369
1$
#1370
0$
#1371
1$
#1372
0$
#1373
1$
#1374
0$
#1375
1$
#1376
0$
#1377
1$
#1378
0$
#1379
1$
#1380
0$
b1001 &
b1000101 #
b1000101 %
#1381
b100100111010001 "
b100100111010001 (
b1001 )
1$
#1382
0$
#1383
1$
#1384
0$
#1385
1$
#1386
0$
#1387
1$
#1388
0$
#1389
1$
#1390
0$
#1391
1$
#1392
0$
#1393
1$
#1394
0$
#1395
1$
#1396
0$
#1397
1$
#1398
0$
#1399
1$
#1400
0$
b1010 &
b1000110 #
b1000110 %
#1401
b100111000110101 "
b100111000110101 (
b1010 )
1$
#1402
0$
#1403
1$
#1404
0$
#1405
1$
#1406
0$
#1407
1$
#1408
0$
#1409
1$
#1410
0$
#1411
1$
#1412
0$
#1413
1$
#1414
0$
#1415
1$
#1416
0$
#1417
1$
#1418
0$
#1419
1$
#1420
0$
b1011 &
b1000111 #
b1000111 %
#1421
b101001011011100 "
b101001011011100 (
b1011 )
1$
#1422
0$
#1423
1$
#1424
0$
#1425
1$
#1426
0$
#1427
1$
#1428
0$
#1429
1$
#1430
0$
#1431
1$
#1432
0$
#1433
1$
#1434
0$
#1435
1$
#1436
0$
#1437
1$
#1438
0$
#1439
1$
#1440
0$
b110 !
b0 &
b100 '
b1001000 #
b1001000 %
#1441
b100 *
b101011111001001 "
b101011111001001 (
b0 )
1$
#1442
0$
#1443
1$
#1444
0$
#1445
1$
#1446
0$
#1447
1$
#1448
0$
#1449
1$
#1450
0$
#1451
1$
#1452
0$
#1453
1$
#1454
0$
#1455
1$
#1456
0$
#1457
1$
#1458
0$
#1459
1$
#1460
0$
b1 &
b1001001 #
b1001001 %
#1461
b101110100000001 "
b101110100000001 (
b1 )
1$
#1462
0$
#1463
1$
#1464
0$
#1465
1$
#1466
0$
#1467
1$
#1468
0$
#1469
1$
#1470
0$
#1471
1$
#1472
0$
#1473
1$
#1474
0$
#1475
1$
#1476
0$
#1477
1$
#1478
0$
#1479
1$
#1480
0$
b10 &
b1001010 #
b1001010 %
#1481
b110001010001001 "
b110001010001001 (
b10 )
1$
#1482
0$
#1483
1$
#1484
0$
#1485
1$
#1486
0$
#1487
1$
#1488
0$
#1489
1$
#1490
0$
#1491
1$
#1492
0$
#1493
1$
#1494
0$
#1495
1$
#1496
0$
#1497
1$
#1498
0$
#1499
1$
#1500
0$
b11 &
b1001011 #
b1001011 %
#1501
b110100001100101 "
b110100001100101 (
b11 )
1$
#1502
0$
#1503
1$
#1504
0$
#1505
1$
#1506
0$
#1507
1$
#1508
0$
#1509
1$
#1510
0$
#1511
1$
#1512
0$
#1513
1$
#1514
0$
#1515
1$
#1516
0$
#1517
1$
#1518
0$
#1519
1$
#1520
0$
b100 &
b1001100 #
b1001100 %
#1521
b110111010011010 "
b110111010011010 (
b100 )
1$
#1522
0$
#1523
1$
